{
  "$schema": "https://developer.microsoft.com/json-schemas/fabric/item/report/definition/visualContainer/2.5.0/schema.json",
  "name": "eae3e2c60bdb11e96b14",
  "position": {
    "x": 104,
    "y": 256,
    "z": 2000,
    "height": 288,
    "width": 376,
    "tabOrder": 2000
  },
  "visual": {
    "visualType": "clusteredColumnChart",
    "query": {
      "queryState": {
        "Category": {
          "projections": [
            {
              "field": {
                "Column": {
                  "Expression": {
                    "SourceRef": {
                      "Entity": "DimDate"
                    }
                  },
                  "Property": "Date_id"
                }
              },
              "queryRef": "DimDate.Date_id",
              "nativeQueryRef": "Date_id",
              "active": true
            }
          ]
        },
        "Y": {
          "projections": [
            {
              "field": {
                "Measure": {
                  "Expression": {
                    "SourceRef": {
                      "Entity": "_Measures"
                    }
                  },
                  "Property": "Sacos de 60 kg Recibidos"
                }
              },
              "queryRef": "_Measures.Sacos de 60 kg Recibidos",
              "nativeQueryRef": "Sacos de 60 kg Recibidos"
            }
          ]
        }
      },
      "sortDefinition": {
        "sort": [
          {
            "field": {
              "Column": {
                "Expression": {
                  "SourceRef": {
                    "Entity": "DimDate"
                  }
                },
                "Property": "Date_id"
              }
            },
            "direction": "Ascending"
          }
        ],
        "isDefaultSort": true
      }
    },
    "objects": {
      "categoryAxis": [
        {
          "properties": {
            "titleText": {
              "expr": {
                "Literal": {
                  "Value": "'Fecha'"
                }
              }
            }
          }
        }
      ]
    },
    "visualContainerObjects": {
      "title": [
        {
          "properties": {
            "text": {
              "expr": {
                "Measure": {
                  "Expression": {
                    "SourceRef": {
                      "Entity": "_Measures"
                    }
                  },
                  "Property": "Tooltip Title"
                }
              }
            }
          }
        }
      ]
    },
    "drillFilterOtherVisuals": true
  }
}