{
  "$schema": "https://developer.microsoft.com/json-schemas/fabric/item/report/definition/page/2.0.0/schema.json",
  "name": "0a46ee561bccde37089d",
  "displayName": "Precio_Carga_Tooltip",
  "displayOption": "ActualSize",
  "height": 240,
  "width": 320,
  "filterConfig": {
    "filters": [
      {
        "name": "6e0cdcd7cb060a9bb007",
        "field": {
          "Column": {
            "Expression": {
              "SourceRef": {
                "Entity": "DimTypes"
              }
            },
            "Property": "Coffee Type"
          }
        },
        "type": "Categorical",
        "howCreated": "Drillthrough"
      }
    ]
  },
  "pageBinding": {
    "name": "1c87beba7d2e69663ecb",
    "type": "Tooltip",
    "parameters": [
      {
        "name": "df0a87a73aeee8368656",
        "boundFilter": "6e0cdcd7cb060a9bb007",
        "fieldExpr": {
          "Column": {
            "Expression": {
              "SourceRef": {
                "Entity": "DimTypes"
              }
            },
            "Property": "Coffee Type"
          }
        }
      }
    ],
    "acceptsFilterContext": "None"
  },
  "objects": {
    "displayArea": [
      {
        "properties": {
          "verticalAlignment": {
            "expr": {
              "Literal": {
                "Value": "'Middle'"
              }
            }
          }
        }
      }
    ]
  },
  "visibility": "HiddenInViewMode",
  "type": "Tooltip"
}